lavapy/__init__.py
lavapy/backoff.py
lavapy/events.py
lavapy/exceptions.py
lavapy/filters.py
lavapy/player.py
lavapy/pool.py
lavapy/queue.py
lavapy/stats.py
lavapy/tracks.py
lavapy/websocket.py
lavapy/ext/spotify/__init__.py
lavapy/ext/spotify/client.py
lavapy/ext/spotify/exceptions.py
lavapy/ext/spotify/tracks.py
nextlava-1.4.2.dist-info/LICENSE
nextlava-1.4.2.dist-info/METADATA
nextlava-1.4.2.dist-info/WHEEL
nextlava-1.4.2.dist-info/top_level.txt
nextlava-1.4.2.dist-info/RECORD
