Metadata-Version: 2.1
Name: nextlava
Version: 1.4.2
Summary: A powerful and robust Python library built from the ground up for interacting with Lavalink.
Home-page: https://github.com/Aspect1103/Lavapy
Author: Aspect1103 & rexwu1104
Author-email: jack.ashwell1@gmail.com
License: MIT
Keywords: lavapy,lavalink,nextocrd
Platform: UNKNOWN
Classifier: License :: OSI Approved :: MIT License
Classifier: Intended Audience :: Developers
Classifier: Natural Language :: English
Classifier: Operating System :: OS Independent
Classifier: Programming Language :: Python :: 3 :: Only
Classifier: Programming Language :: Python :: 3.8
Classifier: Programming Language :: Python :: 3.9
Classifier: Programming Language :: Python :: 3.10
Classifier: Topic :: Internet
Classifier: Topic :: Software Development :: Libraries
Classifier: Topic :: Software Development :: Libraries :: Python Modules
Classifier: Typing :: Typed
Requires-Python: >=3.8
Requires-Dist: nextcord (>=2.0.0a3)
Requires-Dist: aiohttp (>=3.7.4)
Requires-Dist: websocket-client (>=1.2.1)
Requires-Dist: setuptools (>=59.3.0)
